qfinuwa/API.py
qfinuwa/__init__.py
qfinuwa/backtester.py
qfinuwa/indicators.py
qfinuwa/plotting.py
qfinuwa/strategy.py
qfinuwa/opt/__init__.py
qfinuwa/opt/_portfolio.py
qfinuwa/opt/_result.py
qfinuwa/opt/_stockdata.py
qfinuwa-1.1.9.10.dist-info/LICENSE.txt
qfinuwa-1.1.9.10.dist-info/METADATA
qfinuwa-1.1.9.10.dist-info/WHEEL
qfinuwa-1.1.9.10.dist-info/top_level.txt
qfinuwa-1.1.9.10.dist-info/RECORD
