Metadata-Version: 2.1
Name: qfinuwa
Version: 1.1.9.10
Summary: Framework for backtesting quantitative trading algorithims.
Home-page: https://github.com/QFinUWA/algo-backtester/issues
Author: Isaac Bergl
Author-email: tberg644@gmail.com
Project-URL: Bug Tracker, https://github.com/QFinUWA/algo-backtester/issues
Project-URL: repository, https://github.com/QFinUWA/algo-backtester
Classifier: Programming Language :: Python :: 3
Classifier: License :: OSI Approved :: MIT License
Classifier: Operating System :: OS Independent
Requires-Python: >=3.6
License-File: LICENSE.txt
Requires-Dist: tqdm
Requires-Dist: tabulate
Requires-Dist: bokeh
Requires-Dist: requests
